selcraft/cli.py
selcraft/logger.py
selcraft/selcraft
selcraft/version.py
selcraft/generate/build.py
selcraft/generate/config.py
selcraft/spec/schema.1-0-0.json
selcraft/spec/schema.py
selcraft/spec/sample/spec.yaml
selcraft/templates/build.sh.tmpl
selcraft/templates/container.tmpl
selcraft/templates/fc.tmpl
selcraft/templates/if.tmpl
selcraft/templates/makefile.tmpl
selcraft/templates/qm_dropin.tmpl
selcraft/templates/spec.tmpl
selcraft/templates/te.tmpl
selcraft/templates/ipc/shm/allow_rules.tmpl
selcraft/templates/ipc/shm/type_definitions.tmpl
selcraft/templates/ipc/uds/allow_rules.tmpl
selcraft/templates/ipc/uds/type_definitions.tmpl
selcraft/validation/config_validation.py
selcraft/validation/error.py
selcraft/validation/rule.py
selcraft-0.1.1.data/scripts/selcraft
selcraft-0.1.1.dist-info/licenses/LICENSE
selcraft-0.1.1.dist-info/METADATA
selcraft-0.1.1.dist-info/WHEEL
selcraft-0.1.1.dist-info/top_level.txt
selcraft-0.1.1.dist-info/RECORD
