Metadata-Version: 2.4
Name: selcraft
Version: 0.1.1
Summary: Python tool for generating selinux-policy packages to enable cross-environment communication
Author-email: Michael Engel <mengel@redhat.com>
Project-URL: Homepage, https://gitlab.com/mengel1/custom-qm-policy
Project-URL: Documentation, https://gitlab.com/mengel1/custom-qm-policy
Project-URL: Repository, https://gitlab.com/mengel1/custom-qm-policy
Project-URL: Issues, https://gitlab.com/mengel1/custom-qm-policy
Keywords: selinux,policy,generation,QM,ASIL
Classifier: Programming Language :: Python
Classifier: Programming Language :: Python :: 3
Requires-Python: >=3.9
License-File: LICENSE
Requires-Dist: jinja2~=3.1.6
Requires-Dist: jsonschema~=4.23.0
Requires-Dist: pyyaml~=6.0.2
Provides-Extra: dev
Requires-Dist: black~=25.1.0; extra == "dev"
Requires-Dist: isort~=6.0.1; extra == "dev"
Dynamic: license-file
